edx_user_state_client/__init__.py
edx_user_state_client/interface.py
edx_user_state_client/tests.py
edx_user_state_client-1.3.2.dist-info/LICENSE
edx_user_state_client-1.3.2.dist-info/METADATA
edx_user_state_client-1.3.2.dist-info/WHEEL
edx_user_state_client-1.3.2.dist-info/top_level.txt
edx_user_state_client-1.3.2.dist-info/RECORD
